tbevents/__init__.py
tbevents/singleton.py
tbevents/tb_worker.py
tbevents/event_bus/__init__.py
tbevents/event_bus/broker/__init__.py
tbevents/event_bus/broker/broker.py
tbevents/event_bus/broker/broker_configuration.py
tbevents/event_bus/broker/broker_provider.py
tbevents/event_bus/broker/broker_provider_factory.py
tbevents/event_bus/broker/broker_settings.py
tbevents/event_bus/broker/fake_provider/__init__.py
tbevents/event_bus/broker/fake_provider/fake_provider.py
tbevents/event_bus/broker/fake_provider/fake_settings.py
tbevents/event_bus/broker/rabbit/__init__.py
tbevents/event_bus/broker/rabbit/rabbit_provider.py
tbevents/event_bus/broker/rabbit/rabbit_settings.py
tbevents/event_bus/broker/rabbit_pika/__init__.py
tbevents/event_bus/broker/rabbit_pika/rabbit_provider.py
tbevents/event_bus/broker/service_bus/__init__.py
tbevents/event_bus/broker/service_bus/sb_provider.py
tbevents/event_bus/broker/service_bus/sb_settings.py
tbevents/event_bus/models/__init__.py
tbevents/event_bus/models/event.py
tbevents/event_bus/utils/__init__.py
tbevents/event_bus/utils/logger.py
tests/__init__.py
tests/conftest.py
tests/test_event_model.py
tests/test_rabbit_settings.py
tests/test_tbworker.py
tests/integration/__init__.py
tests/integration/service_bus/__init__.py
tests/integration/service_bus/test_tbworker.py
tbevents-1.0.22.dist-info/LICENSE
tbevents-1.0.22.dist-info/METADATA
tbevents-1.0.22.dist-info/WHEEL
tbevents-1.0.22.dist-info/top_level.txt
tbevents-1.0.22.dist-info/RECORD
