Metadata-Version: 2.1
Name: tbevents
Version: 1.0.22
Summary: This library provides functionality for an event-driven architecture using brokers like RabbitMQ or Service Busas Event Bus
Home-page: https://github.com/thingsbuilder/tbevents
Author: Cassio R Eskelsen
Author-email: eskelsen@gmail.com
License: GPL
Platform: UNKNOWN
Classifier: Programming Language :: Python :: 3
Classifier: Programming Language :: Python :: 3.7
License-File: LICENSE
Requires-Dist: kombu
Requires-Dist: python-dateutil
Requires-Dist: pika
